quickfs/__init__.py
quickfs/quickfs.py
quickfs-0.1.1.dist-info/LICENSE
quickfs-0.1.1.dist-info/METADATA
quickfs-0.1.1.dist-info/WHEEL
quickfs-0.1.1.dist-info/top_level.txt
quickfs-0.1.1.dist-info/RECORD
