Metadata-Version: 2.1
Name: quickfs
Version: 0.1.1
Summary: SDK for the QuickFS API
Home-page: https://github.com/LautaroParada/quickfs
Author: Lautaro Parada Opazo
Author-email: lautaro.parada.opazo@email.com
License: Apache License 2.0
Platform: UNKNOWN
